pipq/__init__.py
pipq/pipq.py
pipq/display/__init__.py
pipq/display/display.py
pipq/display/pkgdisplay.py
pipq/display/searchdisplay.py
pipq/display/versionsdisplay.py
pipq/scrape/__init__.py
pipq/scrape/scrape.py
pipq-0.0.2.dist-info/LICENSE
pipq-0.0.2.dist-info/METADATA
pipq-0.0.2.dist-info/WHEEL
pipq-0.0.2.dist-info/entry_points.txt
pipq-0.0.2.dist-info/top_level.txt
pipq-0.0.2.dist-info/RECORD
