Metadata-Version: 1.1
Name: pipq
Version: 0.0.2
Summary: Yet another pip search
Home-page: https://github.com/Error104114/pipq/
Author: Error104114
Author-email: UNKNOWN
License: GPL
Keywords: pipsearch pip search find package python details
Platform: UNKNOWN
Classifier: Development Status :: 2 - Pre-Alpha
Classifier: Operating System :: OS Independent
